c2d_api/__init__.py
c2d_api/api.py
c2d_api-0.0.3.dist-info/METADATA
c2d_api-0.0.3.dist-info/WHEEL
c2d_api-0.0.3.dist-info/top_level.txt
c2d_api-0.0.3.dist-info/RECORD
