Metadata-Version: 2.1
Name: c2d-api
Version: 0.0.3
Summary: Python package for API of Chat2Desk
Home-page: https://github.com/jkasemenov/c2d_api
Author: Evgeniy Semenov
Author-email: jkasemenov@mail.ru
License: UNKNOWN
Keywords: chat2desk,chat,c2d
Platform: UNKNOWN
Classifier: Development Status :: 3 - Alpha
Classifier: Intended Audience :: Developers
Classifier: Topic :: Communications :: Chat :: Internet Relay Chat
Classifier: License :: OSI Approved :: MIT License
Classifier: Programming Language :: Python :: 3
Classifier: Programming Language :: Python :: 3.7
Classifier: Programming Language :: Python :: 3.8
Classifier: Programming Language :: Python :: 3.9
Classifier: Programming Language :: Python :: 3 :: Only
Requires-Python: >=3.7, <4
Requires-Dist: requests
